neo4py/__init__.py
neo4py/neo4py.py
neo4py/sloth.py
neo4py-1.1.5.dist-info/LICENSE
neo4py-1.1.5.dist-info/METADATA
neo4py-1.1.5.dist-info/WHEEL
neo4py-1.1.5.dist-info/top_level.txt
neo4py-1.1.5.dist-info/RECORD
