Metadata-Version: 2.1
Name: neo4py
Version: 1.1.5
Summary: Neo4py is a better alternative to py2neo.
Author-email: Athar Naveed <asphaltlegends24@gmail.com>
Project-URL: Homepage, https://github.com/Athar-Naveed/neo4py
Keywords: neo4j,alternative,neo4py,py2neo,graph database
Classifier: Programming Language :: Python :: 3
Classifier: License :: OSI Approved :: Apache Software License
Classifier: Operating System :: OS Independent
Requires-Python: >=3.8
License-File: LICENSE
Requires-Dist: neo4j >=5.20
